ai_context_manager/__init__.py
ai_context_manager/agent_context_manager.py
ai_context_manager/auto_config.py
ai_context_manager/cli.py
ai_context_manager/config.py
ai_context_manager/context_manager.py
ai_context_manager/feedback.py
ai_context_manager/performance_optimizations.py
ai_context_manager/semantic_agent_context_manager.py
ai_context_manager/semantic_context_manager.py
ai_context_manager/simple_api.py
ai_context_manager/utils.py
ai_context_manager/components/__init__.py
ai_context_manager/components/agent_goal.py
ai_context_manager/components/base.py
ai_context_manager/components/longterm_summary.py
ai_context_manager/components/task_summary.py
ai_context_manager/components/user_summary.py
ai_context_manager/store/__init__.py
ai_context_manager/store/base.py
ai_context_manager/store/json_memory.py
ai_context_manager/store/json_store.py
ai_context_manager/store/postgres_vector_memory.py
ai_context_manager/store/sqlite_store.py
ai_context_manager/store/vector_memory.py
ai_context_manager/summarizers/__init__.py
ai_context_manager/summarizers/auto_fallback_summarizer.py
ai_context_manager/summarizers/base.py
ai_context_manager/summarizers/naive_summarizer.py
ai_context_manager/summarizers/ollama_summarizer.py
ai_context_manager/summarizers/openai_summarizer.py
ai_context_manager-0.2.0.dist-info/licenses/LICENSE
ai_context_manager-0.2.0.dist-info/METADATA
ai_context_manager-0.2.0.dist-info/WHEEL
ai_context_manager-0.2.0.dist-info/entry_points.txt
ai_context_manager-0.2.0.dist-info/top_level.txt
ai_context_manager-0.2.0.dist-info/RECORD
