Metadata-Version: 2.4
Name: ai-context-manager
Version: 0.2.0
Summary: Enterprise-grade context management system for AI agents with vector database support
Author-email: AI Context Manager Team <team@ai-context-manager.com>
Maintainer-email: AI Context Manager Team <team@ai-context-manager.com>
License: MIT
Project-URL: Homepage, https://github.com/ai-context-manager/ai-context-manager
Project-URL: Repository, https://github.com/ai-context-manager/ai-context-manager
Project-URL: Documentation, https://docs.ai-context-manager.com
Project-URL: Issues, https://github.com/ai-context-manager/ai-context-manager/issues
Project-URL: Changelog, https://github.com/ai-context-manager/ai-context-manager/blob/main/CHANGELOG.md
Keywords: ai,context-management,vector-database,agents,llm,embeddings,postgresql,pgvector,chromadb,semantic-search,memory-management
Classifier: Development Status :: 4 - Beta
Classifier: Intended Audience :: Developers
Classifier: License :: OSI Approved :: MIT License
Classifier: Programming Language :: Python :: 3
Classifier: Programming Language :: Python :: 3.9
Classifier: Programming Language :: Python :: 3.10
Classifier: Programming Language :: Python :: 3.11
Classifier: Programming Language :: Python :: 3.12
Classifier: Topic :: Scientific/Engineering :: Artificial Intelligence
Classifier: Topic :: Software Development :: Libraries :: Python Modules
Classifier: Topic :: Database
Classifier: Topic :: Internet :: WWW/HTTP :: Indexing/Search
Requires-Python: >=3.9
License-File: LICENSE
Requires-Dist: openai
Requires-Dist: requests
Requires-Dist: jinja2
Requires-Dist: tiktoken
Requires-Dist: toml
Requires-Dist: urllib3!=2.3.0,>=2.4.0
Provides-Extra: vector
Requires-Dist: chromadb>=0.4.0; extra == "vector"
Requires-Dist: sentence-transformers>=2.2.0; python_version >= "3.10" and extra == "vector"
Provides-Extra: postgres
Requires-Dist: psycopg2-binary>=2.9.0; extra == "postgres"
Requires-Dist: numpy>=1.21.0; extra == "postgres"
Provides-Extra: production
Requires-Dist: psycopg2-binary>=2.9.0; extra == "production"
Requires-Dist: numpy>=1.21.0; extra == "production"
Requires-Dist: sentence-transformers>=2.2.0; python_version >= "3.10" and extra == "production"
Provides-Extra: cli
Requires-Dist: click>=8.0.0; extra == "cli"
Requires-Dist: rich>=10.0.0; extra == "cli"
Provides-Extra: performance
Requires-Dist: psutil>=5.8.0; extra == "performance"
Requires-Dist: memory-profiler>=0.60.0; extra == "performance"
Provides-Extra: all
Requires-Dist: chromadb>=0.4.0; extra == "all"
Requires-Dist: sentence-transformers>=2.2.0; extra == "all"
Requires-Dist: psycopg2-binary>=2.9.0; extra == "all"
Requires-Dist: numpy>=1.21.0; extra == "all"
Requires-Dist: click>=8.0.0; extra == "all"
Requires-Dist: rich>=10.0.0; extra == "all"
Requires-Dist: psutil>=5.8.0; extra == "all"
Dynamic: license-file
